{
  "ts": "2026-05-17T20:24:45Z",
  "command": "npx",
  "args": ["tsx","--test",".worktrees/STORY-028-04/cleargate-cli/test/scripts/codemod-vitest-to-node-test.red.node.test.ts"],
  "cwd": "/Users/ssuladze/Documents/Dev/ClearGate",
  "exit_code": 1,
  "stdout": "▶ STORY-028-04 Scenario 1 — AUTO-CONVERTIBLE plain suite\n  ✖ codemod script exists at cleargate-cli/scripts/codemod-vitest-to-node-test.mjs (2.110042ms)\n  ✖ codemod exits 0 (all files auto-converted) (0.132417ms)\n  ✖ input.vitest.test.ts is renamed to input.node.test.ts (original removed) (0.096458ms)\n  ✖ output matches expected.node.test.ts (after prettier normalization) (0.09425ms)\n✖ STORY-028-04 Scenario 1 — AUTO-CONVERTIBLE plain suite (5.825791ms)\n▶ STORY-028-04 Scenario 2 — all 8 matchers\n  ✖ codemod exits 0 (all-auto: no vi.* calls) (0.333917ms)\n  ✖ output matches expected.node.test.ts (all assert.* mappings correct) (0.141459ms)\n  ✖ output contains assert.strictEqual (toBe converted) (0.108125ms)\n  ✖ output contains assert.deepStrictEqual (toEqual converted) (0.107584ms)\n  ✖ output contains assert.throws (toThrow converted) (0.097375ms)\n  ✖ output contains assert.ok (toBeTruthy/toBeFalsy converted) (0.105791ms)\n  ✖ output does NOT contain vitest import (0.087708ms)\n✖ STORY-028-04 Scenario 2 — all 8 matchers (4.925625ms)\n▶ STORY-028-04 Scenario 3 — vi.mock manual-fix flag\n  ✖ codemod exits 1 (vi.mock triggers manual-fix path) (0.300667ms)\n  ✖ input file is NOT renamed (manual-fix path leaves file untouched) (0.097875ms)\n  ✖ input file bytes are unchanged after codemod (0.080667ms)\n  ✖ manual-fix report exists at default location (0.078792ms)\n  ✖ manual-fix report lists \"vi.mock\" as flagged api (0.075416ms)\n✖ STORY-028-04 Scenario 3 — vi.mock manual-fix flag (2.782417ms)\n▶ STORY-028-04 Scenario 4 — import from 'vitest' rewrite\n  ✖ codemod exits 0 (0.159083ms)\n  ✖ output imports from 'node:test' not 'vitest' (0.079875ms)\n  ✖ output imports assert from 'node:assert/strict' (0.609167ms)\n✖ STORY-028-04 Scenario 4 — import from 'vitest' rewrite (2.952292ms)\n▶ STORY-028-04 Scenario 5 — beforeEach/afterEach hooks\n  ✖ codemod exits 0 (hooks fixture is auto-convertible) (0.211667ms)\n  ✖ output contains beforeEach and afterEach (hooks preserved) (0.097625ms)\n  ✖ output matches expected.node.test.ts fixture (0.10025ms)\n✖ STORY-028-04 Scenario 5 — beforeEach/afterEach hooks (2.373875ms)\n▶ STORY-028-04 Scenario 6 — vi.useFakeTimers manual-fix flag\n  ✖ codemod exits 1 (vi.useFakeTimers triggers manual-fix path) (0.209375ms)\n  ✖ input file is NOT renamed (vi.useFakeTimers = manual-fix) (0.092833ms)\n  ✖ manual-fix report mentions vi.useFakeTimers (0.081792ms)\n✖ STORY-028-04 Scenario 6 — vi.useFakeTimers manual-fix flag (4.463041ms)\n▶ STORY-028-04 Scenario 7 — idempotency\n  ✖ codemod exits 0 on already-converted directory (0.104959ms)\n  ✖ already-converted file is not double-renamed or modified (0.082666ms)\n✖ STORY-028-04 Scenario 7 — idempotency (1.347958ms)\n▶ STORY-028-04 Scenario 8 — exit code 0 on all-auto directory\n  ✖ exit code is 0 when zero MANUAL-FIX-REQUIRED files (0.166625ms)\n✖ STORY-028-04 Scenario 8 — exit code 0 on all-auto directory (1.226375ms)\n▶ STORY-028-04 Scenario 9 — exit code 1 on any-manual directory\n  ✖ exit code is 1 when any MANUAL-FIX-REQUIRED file present (0.193541ms)\n✖ STORY-028-04 Scenario 9 — exit code 1 on any-manual directory (1.422958ms)\nℹ tests 29\nℹ suites 9\nℹ pass 0\nℹ fail 29\nℹ cancelled 0\nℹ skipped 0\nℹ todo 0\nℹ duration_ms 549.44025\n\n✖ failing tests:\n\ntest at .worktrees/STORY-028-04/cleargate-cli/test/scripts/codemod-vitest-to-node-test.red.node.test.ts:3:1097\n✖ codemod script exists at cleargate-cli/scripts/codemod-vitest-to-node-test.mjs (2.110042ms)\n  AssertionError [ERR_ASSERTION]: PRE-FIX GUARD: codemod script does not exist at:\n    /Users/ssuladze/Documents/Dev/ClearGate/.worktrees/STORY-028-04/cleargate-cli/scripts/codemod-vitest-to-node-test.mjs\n  Developer must ship cleargate-cli/scripts/codemod-vitest-to-node-test.mjs.\n      at assertScriptExists (/Users/ssuladze/Documents/Dev/ClearGate/.worktrees/STORY-028-04/cleargate-cli/test/scripts/codemod-vitest-to-node-test.red.node.test.ts:71:10)\n      at TestContext.<anonymous> (/Users/ssuladze/D... [truncated]",
  "stderr": "",
  "agent_type": null,
  "work_item_id": null
}
